{
  "status": "ok",
  "count": 10,
  "count_total": 15,
  "pages": 2,
  "posts": [
    {
      "id": 41,
      "type": "post",
      "slug": "toy-story-that-time-forgot-2014",
      "url": "http://creatives.pk/demos/demo.nayatel/toy-story-that-time-forgot-2014/",
      "status": "publish",
      "title": "Toy Story That Time Forgot (2014)",
      "title_plain": "Toy Story That Time Forgot (2014)",
      "content": "<p><span style=\"color: #333333;\">It&#8217;s a post Christmas play date and the toys have to go up against the fearsome and aggressive new dino toys.</span></p>\n",
      "excerpt": "<p>It&#8217;s a post Christmas play date and the toys have to go up against the fearsome and aggressive new dino toys.</p>\n",
      "date": "2015-11-30 06:10:44",
      "modified": "2015-12-15 10:35:44",
      "categories": [
        {
          "id": 5,
          "slug": "3d",
          "title": "3D",
          "description": "",
          "parent": 4,
          "post_count": 5
        },
        {
          "id": 6,
          "slug": "actionadventure",
          "title": "Action/Adventure",
          "description": "",
          "parent": 4,
          "post_count": 4
        },
        {
          "id": 7,
          "slug": "comedy",
          "title": "Comedy",
          "description": "",
          "parent": 4,
          "post_count": 9
        },
        {
          "id": 8,
          "slug": "drama",
          "title": "Drama",
          "description": "",
          "parent": 4,
          "post_count": 5
        },
        {
          "id": 4,
          "slug": "english-movies",
          "title": "English Movies",
          "description": "",
          "parent": 1,
          "post_count": 12
        },
        {
          "id": 9,
          "slug": "horror-thriller",
          "title": "Horror, Thriller",
          "description": "",
          "parent": 4,
          "post_count": 3
        },
        {
          "id": 10,
          "slug": "kidsfamily",
          "title": "Kids/Family",
          "description": "",
          "parent": 4,
          "post_count": 10
        },
        {
          "id": 1,
          "slug": "vod",
          "title": "vod",
          "description": "",
          "parent": 0,
          "post_count": 13
        }
      ],
      "tags": [],
      "author": {
        "id": 1,
        "slug": "admin",
        "name": "admin",
        "first_name": "",
        "last_name": "",
        "nickname": "admin",
        "url": "",
        "description": ""
      },
      "comments": [],
      "attachments": [
        {
          "id": 42,
          "url": "http://creatives.pk/demos/demo.nayatel/wp-content/uploads/2015/11/13.jpg",
          "slug": "13",
          "title": "13",
          "description": "",
          "caption": "",
          "parent": 41,
          "mime_type": "image/jpeg",
          "images": {
            "full": {
              "url": "http://creatives.pk/demos/demo.nayatel/wp-content/uploads/2015/11/13.jpg",
              "width": 367,
              "height": 544
            },
            "thumbnail": {
              "url": "http://creatives.pk/demos/demo.nayatel/wp-content/uploads/2015/11/13-150x150.jpg",
              "width": 150,
              "height": 150
            },
            "medium": {
              "url": "http://creatives.pk/demos/demo.nayatel/wp-content/uploads/2015/11/13-202x300.jpg",
              "width": 202,
              "height": 300
            },
            "large": {
              "url": "http://creatives.pk/demos/demo.nayatel/wp-content/uploads/2015/11/13.jpg",
              "width": 367,
              "height": 544
            },
            "post-thumbnail": {
              "url": "http://creatives.pk/demos/demo.nayatel/wp-content/uploads/2015/11/13-367x372.jpg",
              "width": 367,
              "height": 372
            },
            "twentyfourteen-full-width": {
              "url": "http://creatives.pk/demos/demo.nayatel/wp-content/uploads/2015/11/13.jpg",
              "width": 367,
              "height": 544
            }
          }
        }
      ],
      "comment_count": 0,
      "comment_status": "open",
      "thumbnail": "http://creatives.pk/demos/demo.nayatel/wp-content/uploads/2015/11/13-367x372.jpg",
      "custom_fields": {
        "name": [
          "Toy.Story.That.Time.Forgot"
        ],
        "episodes": [
          ""
        ],
        "season": [
          ""
        ],
        "type": [
          "Movie"
        ],
        "imdb": [
          "http://www.imdb.com/title/tt3473654/?ref_=nv_sr_2 "
        ],
        "video_url": [
          "http://demovod.nayatel.com/Toy.Story.That.Time.Forgot-HD.mp4"
        ]
      },
      "thumbnail_size": "post-thumbnail",
      "thumbnail_images": {
        "full": {
          "url": "http://creatives.pk/demos/demo.nayatel/wp-content/uploads/2015/11/13.jpg",
          "width": 367,
          "height": 544
        },
        "thumbnail": {
          "url": "http://creatives.pk/demos/demo.nayatel/wp-content/uploads/2015/11/13-150x150.jpg",
          "width": 150,
          "height": 150
        },
        "medium": {
          "url": "http://creatives.pk/demos/demo.nayatel/wp-content/uploads/2015/11/13-202x300.jpg",
          "width": 202,
          "height": 300
        },
        "large": {
          "url": "http://creatives.pk/demos/demo.nayatel/wp-content/uploads/2015/11/13.jpg",
          "width": 367,
          "height": 544
        },
        "post-thumbnail": {
          "url": "http://creatives.pk/demos/demo.nayatel/wp-content/uploads/2015/11/13-367x372.jpg",
          "width": 367,
          "height": 372
        },
        "twentyfourteen-full-width": {
          "url": "http://creatives.pk/demos/demo.nayatel/wp-content/uploads/2015/11/13.jpg",
          "width": 367,
          "height": 544
        }
      }
    },
    {
      "id": 38,
      "type": "post",
      "slug": "tears-of-steel-2012",
      "url": "http://creatives.pk/demos/demo.nayatel/tears-of-steel-2012/",
      "status": "publish",
      "title": "Tears of Steel (2012)",
      "title_plain": "Tears of Steel (2012)",
      "content": "<p><span style=\"color: #333333;\">He just wanted to be awesome in space.</span></p>\n",
      "excerpt": "<p>He just wanted to be awesome in space.</p>\n",
      "date": "2015-11-30 06:08:47",
      "modified": "2015-12-15 10:47:39",
      "categories": [
        {
          "id": 5,
          "slug": "3d",
          "title": "3D",
          "description": "",
          "parent": 4,
          "post_count": 5
        },
        {
          "id": 7,
          "slug": "comedy",
          "title": "Comedy",
          "description": "",
          "parent": 4,
          "post_count": 9
        },
        {
          "id": 4,
          "slug": "english-movies",
          "title": "English Movies",
          "description": "",
          "parent": 1,
          "post_count": 12
        },
        {
          "id": 16,
          "slug": "featured-vod",
          "title": "Featured",
          "description": "",
          "parent": 1,
          "post_count": 3
        },
        {
          "id": 9,
          "slug": "horror-thriller",
          "title": "Horror, Thriller",
          "description": "",
          "parent": 4,
          "post_count": 3
        },
        {
          "id": 10,
          "slug": "kidsfamily",
          "title": "Kids/Family",
          "description": "",
          "parent": 4,
          "post_count": 10
        },
        {
          "id": 13,
          "slug": "sci-fifantasy",
          "title": "Sci-Fi/Fantasy",
          "description": "",
          "parent": 4,
          "post_count": 4
        },
        {
          "id": 14,
          "slug": "short-films",
          "title": "Short Films",
          "description": "",
          "parent": 4,
          "post_count": 8
        },
        {
          "id": 1,
          "slug": "vod",
          "title": "vod",
          "description": "",
          "parent": 0,
          "post_count": 13
        },
        {
          "id": 15,
          "slug": "western",
          "title": "Western",
          "description": "",
          "parent": 4,
          "post_count": 6
        }
      ],
      "tags": [],
      "author": {
        "id": 1,
        "slug": "admin",
        "name": "admin",
        "first_name": "",
        "last_name": "",
        "nickname": "admin",
        "url": "",
        "description": ""
      },
      "comments": [],
      "attachments": [
        {
          "id": 39,
          "url": "http://creatives.pk/demos/demo.nayatel/wp-content/uploads/2015/11/11.jpg",
          "slug": "11",
          "title": "11",
          "description": "",
          "caption": "",
          "parent": 38,
          "mime_type": "image/jpeg",
          "images": {
            "full": {
              "url": "http://creatives.pk/demos/demo.nayatel/wp-content/uploads/2015/11/11.jpg",
              "width": 396,
              "height": 587
            },
            "thumbnail": {
              "url": "http://creatives.pk/demos/demo.nayatel/wp-content/uploads/2015/11/11-150x150.jpg",
              "width": 150,
              "height": 150
            },
            "medium": {
              "url": "http://creatives.pk/demos/demo.nayatel/wp-content/uploads/2015/11/11-202x300.jpg",
              "width": 202,
              "height": 300
            },
            "large": {
              "url": "http://creatives.pk/demos/demo.nayatel/wp-content/uploads/2015/11/11.jpg",
              "width": 396,
              "height": 587
            },
            "post-thumbnail": {
              "url": "http://creatives.pk/demos/demo.nayatel/wp-content/uploads/2015/11/11-396x372.jpg",
              "width": 396,
              "height": 372
            },
            "twentyfourteen-full-width": {
              "url": "http://creatives.pk/demos/demo.nayatel/wp-content/uploads/2015/11/11-396x576.jpg",
              "width": 396,
              "height": 576
            }
          }
        }
      ],
      "comment_count": 0,
      "comment_status": "open",
      "thumbnail": "http://creatives.pk/demos/demo.nayatel/wp-content/uploads/2015/11/11-396x372.jpg",
      "custom_fields": {
        "name": [
          "Tears.Of.Steel"
        ],
        "episodes": [
          ""
        ],
        "season": [
          ""
        ],
        "type": [
          "Movie"
        ],
        "imdb": [
          "http://www.imdb.com/title/tt2285752/"
        ],
        "video_url": [
          "http://demovod.nayatel.com/Tears.Of.Steel-HD.mp4"
        ]
      },
      "thumbnail_size": "post-thumbnail",
      "thumbnail_images": {
        "full": {
          "url": "http://creatives.pk/demos/demo.nayatel/wp-content/uploads/2015/11/11.jpg",
          "width": 396,
          "height": 587
        },
        "thumbnail": {
          "url": "http://creatives.pk/demos/demo.nayatel/wp-content/uploads/2015/11/11-150x150.jpg",
          "width": 150,
          "height": 150
        },
        "medium": {
          "url": "http://creatives.pk/demos/demo.nayatel/wp-content/uploads/2015/11/11-202x300.jpg",
          "width": 202,
          "height": 300
        },
        "large": {
          "url": "http://creatives.pk/demos/demo.nayatel/wp-content/uploads/2015/11/11.jpg",
          "width": 396,
          "height": 587
        },
        "post-thumbnail": {
          "url": "http://creatives.pk/demos/demo.nayatel/wp-content/uploads/2015/11/11-396x372.jpg",
          "width": 396,
          "height": 372
        },
        "twentyfourteen-full-width": {
          "url": "http://creatives.pk/demos/demo.nayatel/wp-content/uploads/2015/11/11-396x576.jpg",
          "width": 396,
          "height": 576
        }
      }
    },
    {
      "id": 34,
      "type": "post",
      "slug": "the-fantastic-flying-books-of-mr-morris-lessmore-2011",
      "url": "http://creatives.pk/demos/demo.nayatel/the-fantastic-flying-books-of-mr-morris-lessmore-2011/",
      "status": "publish",
      "title": "The Fantastic Flying Books of Mr. Morris Lessmore (2011)",
      "title_plain": "The Fantastic Flying Books of Mr. Morris Lessmore (2011)",
      "content": "<p><span style=\"color: #333333;\">After a hurricane levels his city, a young man wanders into a mysterious library where books literally come to life.</span></p>\n",
      "excerpt": "<p>After a hurricane levels his city, a young man wanders into a mysterious library where books literally come to life.</p>\n",
      "date": "2015-11-30 06:05:50",
      "modified": "2015-12-15 10:37:55",
      "categories": [
        {
          "id": 5,
          "slug": "3d",
          "title": "3D",
          "description": "",
          "parent": 4,
          "post_count": 5
        },
        {
          "id": 7,
          "slug": "comedy",
          "title": "Comedy",
          "description": "",
          "parent": 4,
          "post_count": 9
        },
        {
          "id": 4,
          "slug": "english-movies",
          "title": "English Movies",
          "description": "",
          "parent": 1,
          "post_count": 12
        },
        {
          "id": 10,
          "slug": "kidsfamily",
          "title": "Kids/Family",
          "description": "",
          "parent": 4,
          "post_count": 10
        },
        {
          "id": 13,
          "slug": "sci-fifantasy",
          "title": "Sci-Fi/Fantasy",
          "description": "",
          "parent": 4,
          "post_count": 4
        },
        {
          "id": 14,
          "slug": "short-films",
          "title": "Short Films",
          "description": "",
          "parent": 4,
          "post_count": 8
        },
        {
          "id": 1,
          "slug": "vod",
          "title": "vod",
          "description": "",
          "parent": 0,
          "post_count": 13
        },
        {
          "id": 15,
          "slug": "western",
          "title": "Western",
          "description": "",
          "parent": 4,
          "post_count": 6
        }
      ],
      "tags": [],
      "author": {
        "id": 1,
        "slug": "admin",
        "name": "admin",
        "first_name": "",
        "last_name": "",
        "nickname": "admin",
        "url": "",
        "description": ""
      },
      "comments": [],
      "attachments": [
        {
          "id": 35,
          "url": "http://creatives.pk/demos/demo.nayatel/wp-content/uploads/2015/11/10.jpg",
          "slug": "10",
          "title": "10",
          "description": "",
          "caption": "",
          "parent": 34,
          "mime_type": "image/jpeg",
          "images": {
            "full": {
              "url": "http://creatives.pk/demos/demo.nayatel/wp-content/uploads/2015/11/10.jpg",
              "width": 866,
              "height": 482
            },
            "thumbnail": {
              "url": "http://creatives.pk/demos/demo.nayatel/wp-content/uploads/2015/11/10-150x150.jpg",
              "width": 150,
              "height": 150
            },
            "medium": {
              "url": "http://creatives.pk/demos/demo.nayatel/wp-content/uploads/2015/11/10-300x166.jpg",
              "width": 300,
              "height": 166
            },
            "post-thumbnail": {
              "url": "http://creatives.pk/demos/demo.nayatel/wp-content/uploads/2015/11/10-672x372.jpg",
              "width": 672,
              "height": 372
            },
            "twentyfourteen-full-width": {
              "url": "http://creatives.pk/demos/demo.nayatel/wp-content/uploads/2015/11/10.jpg",
              "width": 866,
              "height": 482
            }
          }
        }
      ],
      "comment_count": 0,
      "comment_status": "open",
      "thumbnail": "http://creatives.pk/demos/demo.nayatel/wp-content/uploads/2015/11/10-672x372.jpg",
      "custom_fields": {
        "name": [
          "The.Fantastic.Flying.Books.of.Mr.Morris.Lessmore"
        ],
        "episodes": [
          ""
        ],
        "season": [
          ""
        ],
        "type": [
          "Movie"
        ],
        "imdb": [
          "http://www.imdb.com/title/tt1778342/?ref_=nv_sr_4"
        ],
        "video_url": [
          "http://demovod.nayatel.com/The.Fantastic.Flying.Books.of.Mr.Morris.Lessmore-HD.mp4"
        ]
      },
      "thumbnail_size": "post-thumbnail",
      "thumbnail_images": {
        "full": {
          "url": "http://creatives.pk/demos/demo.nayatel/wp-content/uploads/2015/11/10.jpg",
          "width": 866,
          "height": 482
        },
        "thumbnail": {
          "url": "http://creatives.pk/demos/demo.nayatel/wp-content/uploads/2015/11/10-150x150.jpg",
          "width": 150,
          "height": 150
        },
        "medium": {
          "url": "http://creatives.pk/demos/demo.nayatel/wp-content/uploads/2015/11/10-300x166.jpg",
          "width": 300,
          "height": 166
        },
        "post-thumbnail": {
          "url": "http://creatives.pk/demos/demo.nayatel/wp-content/uploads/2015/11/10-672x372.jpg",
          "width": 672,
          "height": 372
        },
        "twentyfourteen-full-width": {
          "url": "http://creatives.pk/demos/demo.nayatel/wp-content/uploads/2015/11/10.jpg",
          "width": 866,
          "height": 482
        }
      }
    },
    {
      "id": 31,
      "type": "post",
      "slug": "peter-the-wolf-2006",
      "url": "http://creatives.pk/demos/demo.nayatel/peter-the-wolf-2006/",
      "status": "publish",
      "title": "Peter &#038; the Wolf (2006)",
      "title_plain": "Peter &#038; the Wolf (2006)",
      "content": "<p><span style=\"color: #333333;\">An animated retelling set to Prokofiev&#8217;s suite. Peter is a slight lad, solitary, locked out of the woods by his protective grandfather, his only friend a duck. In town, he&#8217;s bullied. When a wolf menaces the duck &#8211; as well as grandfather&#8217;s fat cat and an ill-flying bird that Peter has befriended &#8211; Peter bravely tries to tree the wolf. Grandfather, the townspeople, and the hunters who have antagonized Peter figure in the dénouement.</span></p>\n",
      "excerpt": "<p>An animated retelling set to Prokofiev&#8217;s suite. Peter is a slight lad, solitary, locked out of the woods by his protective grandfather, his only friend a duck. In town, he&#8217;s bullied. When a wolf menaces the duck &#8211; as well as grandfather&#8217;s fat cat and an ill-flying bird that Peter has befriended &#8211; Peter bravely [&hellip;]</p>\n",
      "date": "2015-11-30 06:02:25",
      "modified": "2015-12-15 10:38:34",
      "categories": [
        {
          "id": 5,
          "slug": "3d",
          "title": "3D",
          "description": "",
          "parent": 4,
          "post_count": 5
        },
        {
          "id": 7,
          "slug": "comedy",
          "title": "Comedy",
          "description": "",
          "parent": 4,
          "post_count": 9
        },
        {
          "id": 3,
          "slug": "documentary",
          "title": "Documentary",
          "description": "",
          "parent": 1,
          "post_count": 4
        },
        {
          "id": 4,
          "slug": "english-movies",
          "title": "English Movies",
          "description": "",
          "parent": 1,
          "post_count": 12
        },
        {
          "id": 10,
          "slug": "kidsfamily",
          "title": "Kids/Family",
          "description": "",
          "parent": 4,
          "post_count": 10
        },
        {
          "id": 13,
          "slug": "sci-fifantasy",
          "title": "Sci-Fi/Fantasy",
          "description": "",
          "parent": 4,
          "post_count": 4
        },
        {
          "id": 14,
          "slug": "short-films",
          "title": "Short Films",
          "description": "",
          "parent": 4,
          "post_count": 8
        },
        {
          "id": 1,
          "slug": "vod",
          "title": "vod",
          "description": "",
          "parent": 0,
          "post_count": 13
        }
      ],
      "tags": [],
      "author": {
        "id": 1,
        "slug": "admin",
        "name": "admin",
        "first_name": "",
        "last_name": "",
        "nickname": "admin",
        "url": "",
        "description": ""
      },
      "comments": [],
      "attachments": [
        {
          "id": 32,
          "url": "http://creatives.pk/demos/demo.nayatel/wp-content/uploads/2015/11/9.jpg",
          "slug": "9",
          "title": "9",
          "description": "",
          "caption": "",
          "parent": 31,
          "mime_type": "image/jpeg",
          "images": {
            "full": {
              "url": "http://creatives.pk/demos/demo.nayatel/wp-content/uploads/2015/11/9.jpg",
              "width": 354,
              "height": 500
            },
            "thumbnail": {
              "url": "http://creatives.pk/demos/demo.nayatel/wp-content/uploads/2015/11/9-150x150.jpg",
              "width": 150,
              "height": 150
            },
            "medium": {
              "url": "http://creatives.pk/demos/demo.nayatel/wp-content/uploads/2015/11/9-212x300.jpg",
              "width": 212,
              "height": 300
            },
            "large": {
              "url": "http://creatives.pk/demos/demo.nayatel/wp-content/uploads/2015/11/9.jpg",
              "width": 354,
              "height": 500
            },
            "post-thumbnail": {
              "url": "http://creatives.pk/demos/demo.nayatel/wp-content/uploads/2015/11/9-354x372.jpg",
              "width": 354,
              "height": 372
            },
            "twentyfourteen-full-width": {
              "url": "http://creatives.pk/demos/demo.nayatel/wp-content/uploads/2015/11/9.jpg",
              "width": 354,
              "height": 500
            }
          }
        }
      ],
      "comment_count": 0,
      "comment_status": "open",
      "thumbnail": "http://creatives.pk/demos/demo.nayatel/wp-content/uploads/2015/11/9-354x372.jpg",
      "custom_fields": {
        "name": [
          "Peter.And.The.Wolf"
        ],
        "episodes": [
          ""
        ],
        "season": [
          ""
        ],
        "type": [
          "Movie"
        ],
        "imdb": [
          "http://www.imdb.com/title/tt0863136/?ref_=fn_al_tt_2 "
        ],
        "video_url": [
          "http://demovod.nayatel.com/Peter.And.The.Wolf-HD.mp4"
        ]
      },
      "thumbnail_size": "post-thumbnail",
      "thumbnail_images": {
        "full": {
          "url": "http://creatives.pk/demos/demo.nayatel/wp-content/uploads/2015/11/9.jpg",
          "width": 354,
          "height": 500
        },
        "thumbnail": {
          "url": "http://creatives.pk/demos/demo.nayatel/wp-content/uploads/2015/11/9-150x150.jpg",
          "width": 150,
          "height": 150
        },
        "medium": {
          "url": "http://creatives.pk/demos/demo.nayatel/wp-content/uploads/2015/11/9-212x300.jpg",
          "width": 212,
          "height": 300
        },
        "large": {
          "url": "http://creatives.pk/demos/demo.nayatel/wp-content/uploads/2015/11/9.jpg",
          "width": 354,
          "height": 500
        },
        "post-thumbnail": {
          "url": "http://creatives.pk/demos/demo.nayatel/wp-content/uploads/2015/11/9-354x372.jpg",
          "width": 354,
          "height": 372
        },
        "twentyfourteen-full-width": {
          "url": "http://creatives.pk/demos/demo.nayatel/wp-content/uploads/2015/11/9.jpg",
          "width": 354,
          "height": 500
        }
      }
    },
    {
      "id": 28,
      "type": "post",
      "slug": "paperman-2012",
      "url": "http://creatives.pk/demos/demo.nayatel/paperman-2012/",
      "status": "publish",
      "title": "Paperman (2012)",
      "title_plain": "Paperman (2012)",
      "content": "",
      "excerpt": "",
      "date": "2015-11-30 06:00:56",
      "modified": "2015-12-15 10:39:00",
      "categories": [
        {
          "id": 5,
          "slug": "3d",
          "title": "3D",
          "description": "",
          "parent": 4,
          "post_count": 5
        },
        {
          "id": 6,
          "slug": "actionadventure",
          "title": "Action/Adventure",
          "description": "",
          "parent": 4,
          "post_count": 4
        },
        {
          "id": 8,
          "slug": "drama",
          "title": "Drama",
          "description": "",
          "parent": 4,
          "post_count": 5
        },
        {
          "id": 4,
          "slug": "english-movies",
          "title": "English Movies",
          "description": "",
          "parent": 1,
          "post_count": 12
        },
        {
          "id": 16,
          "slug": "featured-vod",
          "title": "Featured",
          "description": "",
          "parent": 1,
          "post_count": 3
        },
        {
          "id": 10,
          "slug": "kidsfamily",
          "title": "Kids/Family",
          "description": "",
          "parent": 4,
          "post_count": 10
        },
        {
          "id": 12,
          "slug": "romance",
          "title": "Romance",
          "description": "",
          "parent": 4,
          "post_count": 1
        },
        {
          "id": 1,
          "slug": "vod",
          "title": "vod",
          "description": "",
          "parent": 0,
          "post_count": 13
        },
        {
          "id": 15,
          "slug": "western",
          "title": "Western",
          "description": "",
          "parent": 4,
          "post_count": 6
        }
      ],
      "tags": [],
      "author": {
        "id": 1,
        "slug": "admin",
        "name": "admin",
        "first_name": "",
        "last_name": "",
        "nickname": "admin",
        "url": "",
        "description": ""
      },
      "comments": [],
      "attachments": [
        {
          "id": 29,
          "url": "http://creatives.pk/demos/demo.nayatel/wp-content/uploads/2015/11/8.jpg",
          "slug": "8",
          "title": "8",
          "description": "",
          "caption": "",
          "parent": 28,
          "mime_type": "image/jpeg",
          "images": {
            "full": {
              "url": "http://creatives.pk/demos/demo.nayatel/wp-content/uploads/2015/11/8.jpg",
              "width": 373,
              "height": 544
            },
            "thumbnail": {
              "url": "http://creatives.pk/demos/demo.nayatel/wp-content/uploads/2015/11/8-150x150.jpg",
              "width": 150,
              "height": 150
            },
            "medium": {
              "url": "http://creatives.pk/demos/demo.nayatel/wp-content/uploads/2015/11/8-205x300.jpg",
              "width": 205,
              "height": 300
            },
            "large": {
              "url": "http://creatives.pk/demos/demo.nayatel/wp-content/uploads/2015/11/8.jpg",
              "width": 373,
              "height": 544
            },
            "post-thumbnail": {
              "url": "http://creatives.pk/demos/demo.nayatel/wp-content/uploads/2015/11/8-373x372.jpg",
              "width": 373,
              "height": 372
            },
            "twentyfourteen-full-width": {
              "url": "http://creatives.pk/demos/demo.nayatel/wp-content/uploads/2015/11/8.jpg",
              "width": 373,
              "height": 544
            }
          }
        }
      ],
      "comment_count": 0,
      "comment_status": "open",
      "thumbnail": "http://creatives.pk/demos/demo.nayatel/wp-content/uploads/2015/11/8-373x372.jpg",
      "custom_fields": {
        "name": [
          "Paperman"
        ],
        "episodes": [
          ""
        ],
        "season": [
          ""
        ],
        "type": [
          "Movie"
        ],
        "imdb": [
          "http://www.imdb.com/title/tt2388725/ "
        ],
        "video_url": [
          "http://demovod.nayatel.com/Paperman-HD.mp4"
        ]
      },
      "thumbnail_size": "post-thumbnail",
      "thumbnail_images": {
        "full": {
          "url": "http://creatives.pk/demos/demo.nayatel/wp-content/uploads/2015/11/8.jpg",
          "width": 373,
          "height": 544
        },
        "thumbnail": {
          "url": "http://creatives.pk/demos/demo.nayatel/wp-content/uploads/2015/11/8-150x150.jpg",
          "width": 150,
          "height": 150
        },
        "medium": {
          "url": "http://creatives.pk/demos/demo.nayatel/wp-content/uploads/2015/11/8-205x300.jpg",
          "width": 205,
          "height": 300
        },
        "large": {
          "url": "http://creatives.pk/demos/demo.nayatel/wp-content/uploads/2015/11/8.jpg",
          "width": 373,
          "height": 544
        },
        "post-thumbnail": {
          "url": "http://creatives.pk/demos/demo.nayatel/wp-content/uploads/2015/11/8-373x372.jpg",
          "width": 373,
          "height": 372
        },
        "twentyfourteen-full-width": {
          "url": "http://creatives.pk/demos/demo.nayatel/wp-content/uploads/2015/11/8.jpg",
          "width": 373,
          "height": 544
        }
      }
    },
    {
      "id": 25,
      "type": "post",
      "slug": "mr-hublot-2013",
      "url": "http://creatives.pk/demos/demo.nayatel/mr-hublot-2013/",
      "status": "publish",
      "title": "Mr Hublot (2013)",
      "title_plain": "Mr Hublot (2013)",
      "content": "<p><span style=\"color: #333333;\">Mr Hublot is a withdrawn, idiosyncratic character with OCD, scared of change and the outside world. Robot Pet&#8217;s arrival turns his life upside down: he has to share his home with this very invasive companion.</span></p>\n",
      "excerpt": "<p>Mr Hublot is a withdrawn, idiosyncratic character with OCD, scared of change and the outside world. Robot Pet&#8217;s arrival turns his life upside down: he has to share his home with this very invasive companion.</p>\n",
      "date": "2015-11-30 05:59:04",
      "modified": "2015-12-15 10:43:13",
      "categories": [
        {
          "id": 7,
          "slug": "comedy",
          "title": "Comedy",
          "description": "",
          "parent": 4,
          "post_count": 9
        },
        {
          "id": 4,
          "slug": "english-movies",
          "title": "English Movies",
          "description": "",
          "parent": 1,
          "post_count": 12
        },
        {
          "id": 10,
          "slug": "kidsfamily",
          "title": "Kids/Family",
          "description": "",
          "parent": 4,
          "post_count": 10
        },
        {
          "id": 14,
          "slug": "short-films",
          "title": "Short Films",
          "description": "",
          "parent": 4,
          "post_count": 8
        },
        {
          "id": 1,
          "slug": "vod",
          "title": "vod",
          "description": "",
          "parent": 0,
          "post_count": 13
        }
      ],
      "tags": [],
      "author": {
        "id": 1,
        "slug": "admin",
        "name": "admin",
        "first_name": "",
        "last_name": "",
        "nickname": "admin",
        "url": "",
        "description": ""
      },
      "comments": [],
      "attachments": [
        {
          "id": 26,
          "url": "http://creatives.pk/demos/demo.nayatel/wp-content/uploads/2015/11/7.jpg",
          "slug": "7",
          "title": "7",
          "description": "",
          "caption": "",
          "parent": 25,
          "mime_type": "image/jpeg",
          "images": {
            "full": {
              "url": "http://creatives.pk/demos/demo.nayatel/wp-content/uploads/2015/11/7.jpg",
              "width": 386,
              "height": 544
            },
            "thumbnail": {
              "url": "http://creatives.pk/demos/demo.nayatel/wp-content/uploads/2015/11/7-150x150.jpg",
              "width": 150,
              "height": 150
            },
            "medium": {
              "url": "http://creatives.pk/demos/demo.nayatel/wp-content/uploads/2015/11/7-212x300.jpg",
              "width": 212,
              "height": 300
            },
            "large": {
              "url": "http://creatives.pk/demos/demo.nayatel/wp-content/uploads/2015/11/7.jpg",
              "width": 386,
              "height": 544
            },
            "post-thumbnail": {
              "url": "http://creatives.pk/demos/demo.nayatel/wp-content/uploads/2015/11/7-386x372.jpg",
              "width": 386,
              "height": 372
            },
            "twentyfourteen-full-width": {
              "url": "http://creatives.pk/demos/demo.nayatel/wp-content/uploads/2015/11/7.jpg",
              "width": 386,
              "height": 544
            }
          }
        }
      ],
      "comment_count": 0,
      "comment_status": "open",
      "thumbnail": "http://creatives.pk/demos/demo.nayatel/wp-content/uploads/2015/11/7-386x372.jpg",
      "custom_fields": {
        "name": [
          "Mr.Hublot"
        ],
        "episodes": [
          ""
        ],
        "season": [
          ""
        ],
        "type": [
          "Movie"
        ],
        "imdb": [
          "http://www.imdb.com/title/tt3043542/?ref_=nv_sr_1 "
        ],
        "video_url": [
          "http://demovod.nayatel.com/Mr.Hublot-HD.mp4"
        ]
      },
      "thumbnail_size": "post-thumbnail",
      "thumbnail_images": {
        "full": {
          "url": "http://creatives.pk/demos/demo.nayatel/wp-content/uploads/2015/11/7.jpg",
          "width": 386,
          "height": 544
        },
        "thumbnail": {
          "url": "http://creatives.pk/demos/demo.nayatel/wp-content/uploads/2015/11/7-150x150.jpg",
          "width": 150,
          "height": 150
        },
        "medium": {
          "url": "http://creatives.pk/demos/demo.nayatel/wp-content/uploads/2015/11/7-212x300.jpg",
          "width": 212,
          "height": 300
        },
        "large": {
          "url": "http://creatives.pk/demos/demo.nayatel/wp-content/uploads/2015/11/7.jpg",
          "width": 386,
          "height": 544
        },
        "post-thumbnail": {
          "url": "http://creatives.pk/demos/demo.nayatel/wp-content/uploads/2015/11/7-386x372.jpg",
          "width": 386,
          "height": 372
        },
        "twentyfourteen-full-width": {
          "url": "http://creatives.pk/demos/demo.nayatel/wp-content/uploads/2015/11/7.jpg",
          "width": 386,
          "height": 544
        }
      }
    },
    {
      "id": 22,
      "type": "post",
      "slug": "god-of-love-2010",
      "url": "http://creatives.pk/demos/demo.nayatel/god-of-love-2010/",
      "status": "publish",
      "title": "God of Love (2010)",
      "title_plain": "God of Love (2010)",
      "content": "",
      "excerpt": "",
      "date": "2015-11-30 05:56:40",
      "modified": "2015-12-15 10:39:29",
      "categories": [
        {
          "id": 3,
          "slug": "documentary",
          "title": "Documentary",
          "description": "",
          "parent": 1,
          "post_count": 4
        },
        {
          "id": 8,
          "slug": "drama",
          "title": "Drama",
          "description": "",
          "parent": 4,
          "post_count": 5
        },
        {
          "id": 4,
          "slug": "english-movies",
          "title": "English Movies",
          "description": "",
          "parent": 1,
          "post_count": 12
        },
        {
          "id": 1,
          "slug": "vod",
          "title": "vod",
          "description": "",
          "parent": 0,
          "post_count": 13
        },
        {
          "id": 15,
          "slug": "western",
          "title": "Western",
          "description": "",
          "parent": 4,
          "post_count": 6
        }
      ],
      "tags": [],
      "author": {
        "id": 1,
        "slug": "admin",
        "name": "admin",
        "first_name": "",
        "last_name": "",
        "nickname": "admin",
        "url": "",
        "description": ""
      },
      "comments": [],
      "attachments": [
        {
          "id": 23,
          "url": "http://creatives.pk/demos/demo.nayatel/wp-content/uploads/2015/11/6.jpg",
          "slug": "6",
          "title": "6",
          "description": "",
          "caption": "",
          "parent": 22,
          "mime_type": "image/jpeg",
          "images": {
            "full": {
              "url": "http://creatives.pk/demos/demo.nayatel/wp-content/uploads/2015/11/6.jpg",
              "width": 440,
              "height": 587
            },
            "thumbnail": {
              "url": "http://creatives.pk/demos/demo.nayatel/wp-content/uploads/2015/11/6-150x150.jpg",
              "width": 150,
              "height": 150
            },
            "medium": {
              "url": "http://creatives.pk/demos/demo.nayatel/wp-content/uploads/2015/11/6-224x300.jpg",
              "width": 224,
              "height": 300
            },
            "large": {
              "url": "http://creatives.pk/demos/demo.nayatel/wp-content/uploads/2015/11/6.jpg",
              "width": 440,
              "height": 587
            },
            "post-thumbnail": {
              "url": "http://creatives.pk/demos/demo.nayatel/wp-content/uploads/2015/11/6-440x372.jpg",
              "width": 440,
              "height": 372
            },
            "twentyfourteen-full-width": {
              "url": "http://creatives.pk/demos/demo.nayatel/wp-content/uploads/2015/11/6-440x576.jpg",
              "width": 440,
              "height": 576
            }
          }
        }
      ],
      "comment_count": 0,
      "comment_status": "open",
      "thumbnail": "http://creatives.pk/demos/demo.nayatel/wp-content/uploads/2015/11/6-440x372.jpg",
      "custom_fields": {
        "name": [
          "God.Of.Love"
        ],
        "episodes": [
          ""
        ],
        "season": [
          ""
        ],
        "type": [
          "Movie"
        ],
        "imdb": [
          "http://www.imdb.com/title/tt1631323/?ref_=fn_al_tt_1"
        ],
        "video_url": [
          "http://demovod.nayatel.com/God.Of.Love-HD.mp4"
        ]
      },
      "thumbnail_size": "post-thumbnail",
      "thumbnail_images": {
        "full": {
          "url": "http://creatives.pk/demos/demo.nayatel/wp-content/uploads/2015/11/6.jpg",
          "width": 440,
          "height": 587
        },
        "thumbnail": {
          "url": "http://creatives.pk/demos/demo.nayatel/wp-content/uploads/2015/11/6-150x150.jpg",
          "width": 150,
          "height": 150
        },
        "medium": {
          "url": "http://creatives.pk/demos/demo.nayatel/wp-content/uploads/2015/11/6-224x300.jpg",
          "width": 224,
          "height": 300
        },
        "large": {
          "url": "http://creatives.pk/demos/demo.nayatel/wp-content/uploads/2015/11/6.jpg",
          "width": 440,
          "height": 587
        },
        "post-thumbnail": {
          "url": "http://creatives.pk/demos/demo.nayatel/wp-content/uploads/2015/11/6-440x372.jpg",
          "width": 440,
          "height": 372
        },
        "twentyfourteen-full-width": {
          "url": "http://creatives.pk/demos/demo.nayatel/wp-content/uploads/2015/11/6-440x576.jpg",
          "width": 440,
          "height": 576
        }
      }
    },
    {
      "id": 19,
      "type": "post",
      "slug": "frozen-fever-2015",
      "url": "http://creatives.pk/demos/demo.nayatel/frozen-fever-2015/",
      "status": "publish",
      "title": "Frozen Fever (2015)",
      "title_plain": "Frozen Fever (2015)",
      "content": "<p><span style=\"color: #333333;\">On Anna&#8217;s birthday, Elsa and Kristoff are determined to give her the best celebration ever, but Elsa&#8217;s icy powers may put more than just the party at risk.</span></p>\n",
      "excerpt": "<p>On Anna&#8217;s birthday, Elsa and Kristoff are determined to give her the best celebration ever, but Elsa&#8217;s icy powers may put more than just the party at risk.</p>\n",
      "date": "2015-11-30 05:55:11",
      "modified": "2015-12-15 10:39:49",
      "categories": [
        {
          "id": 6,
          "slug": "actionadventure",
          "title": "Action/Adventure",
          "description": "",
          "parent": 4,
          "post_count": 4
        },
        {
          "id": 7,
          "slug": "comedy",
          "title": "Comedy",
          "description": "",
          "parent": 4,
          "post_count": 9
        },
        {
          "id": 3,
          "slug": "documentary",
          "title": "Documentary",
          "description": "",
          "parent": 1,
          "post_count": 4
        },
        {
          "id": 4,
          "slug": "english-movies",
          "title": "English Movies",
          "description": "",
          "parent": 1,
          "post_count": 12
        },
        {
          "id": 16,
          "slug": "featured-vod",
          "title": "Featured",
          "description": "",
          "parent": 1,
          "post_count": 3
        },
        {
          "id": 10,
          "slug": "kidsfamily",
          "title": "Kids/Family",
          "description": "",
          "parent": 4,
          "post_count": 10
        },
        {
          "id": 14,
          "slug": "short-films",
          "title": "Short Films",
          "description": "",
          "parent": 4,
          "post_count": 8
        },
        {
          "id": 1,
          "slug": "vod",
          "title": "vod",
          "description": "",
          "parent": 0,
          "post_count": 13
        }
      ],
      "tags": [],
      "author": {
        "id": 1,
        "slug": "admin",
        "name": "admin",
        "first_name": "",
        "last_name": "",
        "nickname": "admin",
        "url": "",
        "description": ""
      },
      "comments": [],
      "attachments": [
        {
          "id": 20,
          "url": "http://creatives.pk/demos/demo.nayatel/wp-content/uploads/2015/11/5.jpg",
          "slug": "5",
          "title": "5",
          "description": "",
          "caption": "",
          "parent": 19,
          "mime_type": "image/jpeg",
          "images": {
            "full": {
              "url": "http://creatives.pk/demos/demo.nayatel/wp-content/uploads/2015/11/5.jpg",
              "width": 783,
              "height": 587
            },
            "thumbnail": {
              "url": "http://creatives.pk/demos/demo.nayatel/wp-content/uploads/2015/11/5-150x150.jpg",
              "width": 150,
              "height": 150
            },
            "medium": {
              "url": "http://creatives.pk/demos/demo.nayatel/wp-content/uploads/2015/11/5-300x224.jpg",
              "width": 300,
              "height": 224
            },
            "post-thumbnail": {
              "url": "http://creatives.pk/demos/demo.nayatel/wp-content/uploads/2015/11/5-672x372.jpg",
              "width": 672,
              "height": 372
            },
            "twentyfourteen-full-width": {
              "url": "http://creatives.pk/demos/demo.nayatel/wp-content/uploads/2015/11/5-783x576.jpg",
              "width": 783,
              "height": 576
            }
          }
        }
      ],
      "comment_count": 0,
      "comment_status": "open",
      "thumbnail": "http://creatives.pk/demos/demo.nayatel/wp-content/uploads/2015/11/5-672x372.jpg",
      "custom_fields": {
        "name": [
          "Frozen.Fever"
        ],
        "episodes": [
          ""
        ],
        "season": [
          ""
        ],
        "type": [
          "Movie"
        ],
        "imdb": [
          "http://www.imdb.com/title/tt4007502/?ref_=nv_sr_1"
        ],
        "video_url": [
          "http://demovod.nayatel.com/Frozen.Fever-HD.mp4"
        ]
      },
      "thumbnail_size": "post-thumbnail",
      "thumbnail_images": {
        "full": {
          "url": "http://creatives.pk/demos/demo.nayatel/wp-content/uploads/2015/11/5.jpg",
          "width": 783,
          "height": 587
        },
        "thumbnail": {
          "url": "http://creatives.pk/demos/demo.nayatel/wp-content/uploads/2015/11/5-150x150.jpg",
          "width": 150,
          "height": 150
        },
        "medium": {
          "url": "http://creatives.pk/demos/demo.nayatel/wp-content/uploads/2015/11/5-300x224.jpg",
          "width": 300,
          "height": 224
        },
        "post-thumbnail": {
          "url": "http://creatives.pk/demos/demo.nayatel/wp-content/uploads/2015/11/5-672x372.jpg",
          "width": 672,
          "height": 372
        },
        "twentyfourteen-full-width": {
          "url": "http://creatives.pk/demos/demo.nayatel/wp-content/uploads/2015/11/5-783x576.jpg",
          "width": 783,
          "height": 576
        }
      }
    }
  ]
}
